multimind/__init__.py
multimind/main_config.py
multimind/agents/__init__.py
multimind/agents/agent.py
multimind/agents/agent_loader.py
multimind/agents/agent_registry.py
multimind/agents/memory.py
multimind/agents/prompt_correction.py
multimind/agents/react_toolchain.py
multimind/agents/tools/__init__.py
multimind/agents/tools/base.py
multimind/agents/tools/calculator.py
multimind/api/__init__.py
multimind/api/multi_model_api.py
multimind/api/unified_api.py
multimind/api/mcp/__init__.py
multimind/api/mcp/base.py
multimind/api/mcp/registry.py
multimind/cli/__init__.py
multimind/cli/__main__.py
multimind/cli/chat.py
multimind/cli/compliance.py
multimind/cli/config.py
multimind/cli/context_transfer.py
multimind/cli/model_conversion_cli.py
multimind/cli/models.py
multimind/cli/multi_model_cli.py
multimind/client/__init__.py
multimind/client/federated_router.py
multimind/client/model_client.py
multimind/client/rag_client.py
multimind/compliance/__init__.py
multimind/compliance/accessibility.py
multimind/compliance/advanced.py
multimind/compliance/advanced_config.py
multimind/compliance/ai_act.py
multimind/compliance/ai_frameworks.py
multimind/compliance/audit.py
multimind/compliance/config.py
multimind/compliance/corporate.py
multimind/compliance/data_protection.py
multimind/compliance/data_transfer.py
multimind/compliance/financial.py
multimind/compliance/gdpr.py
multimind/compliance/governance.py
multimind/compliance/healthcare.py
multimind/compliance/iso.py
multimind/compliance/model_training.py
multimind/compliance/policies.py
multimind/compliance/privacy.py
multimind/compliance/risk_assessment.py
multimind/compliance/supply_chain.py
multimind/compliance/visualization.py
multimind/config/__init__.py
multimind/config/moe_config.py
multimind/config/multi_modal_config.py
multimind/context_transfer/__init__.py
multimind/context_transfer/adapters.py
multimind/context_transfer/api.py
multimind/context_transfer/manager.py
multimind/context_window/__init__.py
multimind_sdk-0.2.2.dist-info/licenses/LICENSE
multimind_sdk-0.2.2.dist-info/METADATA
multimind_sdk-0.2.2.dist-info/WHEEL
multimind_sdk-0.2.2.dist-info/entry_points.txt
multimind_sdk-0.2.2.dist-info/top_level.txt
multimind_sdk-0.2.2.dist-info/RECORD
