Metadata-Version: 2.4
Name: multimind-sdk
Version: 0.2.2
Summary: The Future of AI Development - 60+ Vector Databases • 100+ AI Models • Quantum Memory • Hybrid RAG • Enterprise Compliance
Home-page: https://github.com/multimind-dev/multimind-sdk
Author: AI2Innovate Team
Author-email: contact@multimind.dev
Project-URL: Bug Tracker, https://github.com/multimind-dev/multimind-sdk/issues
Project-URL: Website, https://multimind.dev
Project-URL: Source Code, https://github.com/multimind-dev/multimind-sdk
Project-URL: Discord, https://discord.gg/K64U65je7h
Project-URL: OpenCollective, https://opencollective.com/multimind-sdk
Keywords: ai,artificial-intelligence,llm,machine-learning,rag,vector-database,agents,fine-tuning,quantum-memory,hybrid-rag,enterprise-ai,compliance,multi-modal,federated-learning,self-evolving-agents,mcp,workflow-automation
Classifier: Development Status :: 4 - Beta
Classifier: Intended Audience :: Developers
Classifier: Intended Audience :: Science/Research
Classifier: License :: OSI Approved :: Apache Software License
Classifier: Operating System :: OS Independent
Classifier: Programming Language :: Python :: 3
Classifier: Programming Language :: Python :: 3.8
Classifier: Programming Language :: Python :: 3.9
Classifier: Programming Language :: Python :: 3.10
Classifier: Programming Language :: Python :: 3.11
Classifier: Programming Language :: Python :: 3.12
Classifier: Topic :: Scientific/Engineering :: Artificial Intelligence
Classifier: Topic :: Software Development :: Libraries :: Python Modules
Classifier: Topic :: Software Development :: Libraries :: Application Frameworks
Classifier: Topic :: Text Processing :: Linguistic
Classifier: Topic :: Database :: Database Engines/Servers
Classifier: Topic :: Internet :: WWW/HTTP :: Dynamic Content
Classifier: Topic :: System :: Distributed Computing
Classifier: Topic :: System :: Systems Administration
Classifier: Topic :: Utilities
Requires-Python: >=3.8
License-File: LICENSE
Requires-Dist: openai==1.82.0
Requires-Dist: anthropic==0.52.1
Requires-Dist: pydantic==2.11.5
Requires-Dist: pydantic-settings>=2.0.0
Requires-Dist: python-dotenv==1.1.0
Requires-Dist: tiktoken==0.9.0
Requires-Dist: spacy>=3.8.7
Requires-Dist: nltk==3.9.1
Requires-Dist: fastapi==0.115.9
Requires-Dist: python-jose==3.5.0
Requires-Dist: python-multipart==0.0.20
Requires-Dist: aiohttp==3.12.2
Requires-Dist: uvicorn==0.34.2
Requires-Dist: click==8.1.8
Requires-Dist: rich==14.0.0
Requires-Dist: requests==2.32.3
Requires-Dist: typing-extensions==4.13.2
Requires-Dist: PyYAML==6.0.2
Requires-Dist: beautifulsoup4==4.12.2
Requires-Dist: opencv-python==4.11.0.86
Requires-Dist: pillow==11.2.1
Requires-Dist: PyPDF2==3.0.1
Requires-Dist: python-docx==1.1.2
Requires-Dist: attrs==25.3.0
Requires-Dist: certifi==2025.4.26
Requires-Dist: charset-normalizer==3.4.2
Requires-Dist: idna==3.10
Requires-Dist: numpy==2.2.6
Requires-Dist: scikit-learn==1.6.1
Requires-Dist: scipy==1.15.3
Requires-Dist: pandas==2.2.3
Requires-Dist: matplotlib==3.10.3
Requires-Dist: seaborn==0.13.2
Requires-Dist: selenium==4.15.2
Requires-Dist: lxml==5.4.0
Requires-Dist: joblib==1.5.1
Requires-Dist: pytest==8.3.5
Requires-Dist: pytest-asyncio==1.0.0
Requires-Dist: black==25.1.0
Requires-Dist: isort==6.0.1
Requires-Dist: mypy==1.15.0
Requires-Dist: ruff==0.11.11
Requires-Dist: python-pptx
Requires-Dist: unstructured
Requires-Dist: pytesseract
Requires-Dist: sentence-transformers==4.1.0
Provides-Extra: dev
Requires-Dist: pytest>=7.0.0; extra == "dev"
Requires-Dist: pytest-asyncio>=0.21.0; extra == "dev"
Requires-Dist: black>=23.0.0; extra == "dev"
Requires-Dist: isort>=5.12.0; extra == "dev"
Requires-Dist: mypy>=1.0.0; extra == "dev"
Requires-Dist: ruff>=0.1.0; extra == "dev"
Requires-Dist: pre-commit>=3.0.0; extra == "dev"
Provides-Extra: compliance
Requires-Dist: cryptography>=41.0.0; extra == "compliance"
Requires-Dist: pyjwt>=2.8.0; extra == "compliance"
Requires-Dist: bcrypt>=4.0.0; extra == "compliance"
Provides-Extra: gateway
Requires-Dist: fastapi>=0.68.0; extra == "gateway"
Requires-Dist: uvicorn>=0.15.0; extra == "gateway"
Requires-Dist: groq>=0.3.0; extra == "gateway"
Requires-Dist: huggingface-hub>=0.16.0; extra == "gateway"
Requires-Dist: httpx>=0.23.0; extra == "gateway"
Requires-Dist: pytest-cov>=2.12.0; extra == "gateway"
Provides-Extra: full
Requires-Dist: accelerate==1.7.0; extra == "full"
Requires-Dist: aiohappyeyeballs==2.6.1; extra == "full"
Requires-Dist: aiohttp==3.12.2; extra == "full"
Requires-Dist: aiosignal==1.3.2; extra == "full"
Requires-Dist: annotated-types==0.7.0; extra == "full"
Requires-Dist: anthropic==0.52.1; extra == "full"
Requires-Dist: anyio==4.9.0; extra == "full"
Requires-Dist: asgiref==3.8.1; extra == "full"
Requires-Dist: async-timeout==5.0.1; extra == "full"
Requires-Dist: attrs==25.3.0; extra == "full"
Requires-Dist: backoff==2.2.1; extra == "full"
Requires-Dist: backports.tarfile==1.2.0; extra == "full"
Requires-Dist: bcrypt==4.3.0; extra == "full"
Requires-Dist: beautifulsoup4==4.12.2; extra == "full"
Requires-Dist: bitsandbytes>=0.42.0; extra == "full"
Requires-Dist: black==25.1.0; extra == "full"
Requires-Dist: build==1.2.2.post1; extra == "full"
Requires-Dist: cachetools==5.5.2; extra == "full"
Requires-Dist: certifi==2025.4.26; extra == "full"
Requires-Dist: cffi==1.17.1; extra == "full"
Requires-Dist: charset-normalizer==3.4.2; extra == "full"
Requires-Dist: chromadb==1.0.10; extra == "full"
Requires-Dist: click==8.1.8; extra == "full"
Requires-Dist: colorama==0.4.6; extra == "full"
Requires-Dist: coloredlogs==15.0.1; extra == "full"
Requires-Dist: cryptography==45.0.2; extra == "full"
Requires-Dist: datasets==3.6.0; extra == "full"
Requires-Dist: Deprecated==1.2.18; extra == "full"
Requires-Dist: dill==0.3.8; extra == "full"
Requires-Dist: distro==1.9.0; extra == "full"
Requires-Dist: docutils==0.21.2; extra == "full"
Requires-Dist: durationpy==0.10; extra == "full"
Requires-Dist: EbookLib==0.19; extra == "full"
Requires-Dist: ecdsa==0.19.1; extra == "full"
Requires-Dist: eval_type_backport==0.2.2; extra == "full"
Requires-Dist: exceptiongroup==1.3.0; extra == "full"
Requires-Dist: faiss-cpu==1.11.0; extra == "full"
Requires-Dist: fastapi==0.115.9; extra == "full"
Requires-Dist: filelock==3.18.0; extra == "full"
Requires-Dist: flatbuffers==25.2.10; extra == "full"
Requires-Dist: frozenlist==1.6.0; extra == "full"
Requires-Dist: fsspec==2025.3.0; extra == "full"
Requires-Dist: google-auth==2.40.2; extra == "full"
Requires-Dist: googleapis-common-protos==1.70.0; extra == "full"
Requires-Dist: greenlet==3.2.2; extra == "full"
Requires-Dist: grpcio==1.71.0; extra == "full"
Requires-Dist: h11==0.16.0; extra == "full"
Requires-Dist: hippo-api==1.1.0rc3; extra == "full"
Requires-Dist: httpcore==1.0.9; extra == "full"
Requires-Dist: httptools==0.6.4; extra == "full"
Requires-Dist: httpx==0.28.1; extra == "full"
Requires-Dist: huggingface-hub==0.32.0; extra == "full"
Requires-Dist: humanfriendly==10.0; extra == "full"
Requires-Dist: id==1.5.0; extra == "full"
Requires-Dist: idna==3.10; extra == "full"
Requires-Dist: importlib_metadata==8.6.1; extra == "full"
Requires-Dist: importlib_resources==6.5.2; extra == "full"
Requires-Dist: iniconfig==2.1.0; extra == "full"
Requires-Dist: isort==6.0.1; extra == "full"
Requires-Dist: jaraco.classes==3.4.0; extra == "full"
Requires-Dist: jaraco.context==6.0.1; extra == "full"
Requires-Dist: jaraco.functools==4.1.0; extra == "full"
Requires-Dist: Jinja2==3.1.6; extra == "full"
Requires-Dist: jiter==0.10.0; extra == "full"
Requires-Dist: joblib==1.5.1; extra == "full"
Requires-Dist: jsonschema==4.23.0; extra == "full"
Requires-Dist: jsonschema-specifications==2025.4.1; extra == "full"
Requires-Dist: keyring==25.6.0; extra == "full"
Requires-Dist: kubernetes==32.0.1; extra == "full"
Requires-Dist: lxml==5.4.0; extra == "full"
Requires-Dist: markdown-it-py==3.0.0; extra == "full"
Requires-Dist: MarkupSafe==3.0.2; extra == "full"
Requires-Dist: matplotlib==3.10.3; extra == "full"
Requires-Dist: mdurl==0.1.2; extra == "full"
Requires-Dist: mistralai==1.8.1; extra == "full"
Requires-Dist: mmh3==5.1.0; extra == "full"
Requires-Dist: more-itertools==10.7.0; extra == "full"
Requires-Dist: mpmath==1.3.0; extra == "full"
Requires-Dist: multidict==6.4.4; extra == "full"
Requires-Dist: multiprocess==0.70.16; extra == "full"
Requires-Dist: mypy==1.15.0; extra == "full"
Requires-Dist: mypy_extensions==1.1.0; extra == "full"
Requires-Dist: networkx==3.4.2; extra == "full"
Requires-Dist: nh3==0.2.21; extra == "full"
Requires-Dist: nltk==3.9.1; extra == "full"
Requires-Dist: numpy>=2.2.6; extra == "full"
Requires-Dist: oauthlib==3.2.2; extra == "full"
Requires-Dist: onnxruntime>=1.22.0; extra == "full"
Requires-Dist: onnx>=1.18.0; extra == "full"
Requires-Dist: openai==1.82.0; extra == "full"
Requires-Dist: opencv-python==4.11.0.86; extra == "full"
Requires-Dist: opentelemetry-api==1.33.1; extra == "full"
Requires-Dist: opentelemetry-exporter-otlp-proto-common==1.33.1; extra == "full"
Requires-Dist: opentelemetry-exporter-otlp-proto-grpc==1.33.1; extra == "full"
Requires-Dist: opentelemetry-instrumentation==0.54b1; extra == "full"
Requires-Dist: opentelemetry-instrumentation-asgi==0.54b1; extra == "full"
Requires-Dist: opentelemetry-instrumentation-fastapi==0.54b1; extra == "full"
Requires-Dist: opentelemetry-proto==1.33.1; extra == "full"
Requires-Dist: opentelemetry-sdk==1.33.1; extra == "full"
Requires-Dist: opentelemetry-semantic-conventions==0.54b1; extra == "full"
Requires-Dist: opentelemetry-util-http==0.54b1; extra == "full"
Requires-Dist: orjson==3.10.18; extra == "full"
Requires-Dist: overrides==7.7.0; extra == "full"
Requires-Dist: packaging==25.0; extra == "full"
Requires-Dist: pandas>=2.2.3; extra == "full"
Requires-Dist: pathspec==0.12.1; extra == "full"
Requires-Dist: pdf2image==1.17.0; extra == "full"
Requires-Dist: peft>=0.7.0; extra == "full"
Requires-Dist: pillow==11.2.1; extra == "full"
Requires-Dist: pinecone-client==6.0.0; extra == "full"
Requires-Dist: pinecone-plugin-interface==0.0.7; extra == "full"
Requires-Dist: platformdirs==4.3.8; extra == "full"
Requires-Dist: pluggy==1.6.0; extra == "full"
Requires-Dist: posthog==4.1.0; extra == "full"
Requires-Dist: propcache==0.3.1; extra == "full"
Requires-Dist: protobuf==5.29.4; extra == "full"
Requires-Dist: psutil==7.0.0; extra == "full"
Requires-Dist: pyarrow==20.0.0; extra == "full"
Requires-Dist: pyasn1==0.6.1; extra == "full"
Requires-Dist: pyasn1_modules==0.4.1; extra == "full"
Requires-Dist: pycparser==2.22; extra == "full"
Requires-Dist: pydantic==2.11.5; extra == "full"
Requires-Dist: pydantic_core==2.33.2; extra == "full"
Requires-Dist: pydantic-settings==2.4.0; extra == "full"
Requires-Dist: Pygments==2.19.1; extra == "full"
Requires-Dist: PyPDF2==3.0.1; extra == "full"
Requires-Dist: PyPika==0.48.9; extra == "full"
Requires-Dist: pyproject_hooks==1.2.0; extra == "full"
Requires-Dist: pyreadline3==3.5.4; extra == "full"
Requires-Dist: pytesseract==0.3.13; extra == "full"
Requires-Dist: pytest==8.3.5; extra == "full"
Requires-Dist: pytest-asyncio==1.0.0; extra == "full"
Requires-Dist: python-dateutil==2.9.0.post0; extra == "full"
Requires-Dist: python-docx==1.1.2; extra == "full"
Requires-Dist: python-dotenv==1.1.0; extra == "full"
Requires-Dist: python-jose==3.5.0; extra == "full"
Requires-Dist: python-multipart==0.0.20; extra == "full"
Requires-Dist: pytz==2025.2; extra == "full"
Requires-Dist: pywin32-ctypes==0.2.3; extra == "full"
Requires-Dist: PyYAML==6.0.2; extra == "full"
Requires-Dist: readme_renderer==44.0; extra == "full"
Requires-Dist: referencing==0.36.2; extra == "full"
Requires-Dist: regex==2024.11.6; extra == "full"
Requires-Dist: requests==2.32.3; extra == "full"
Requires-Dist: requests-oauthlib==2.0.0; extra == "full"
Requires-Dist: requests-toolbelt==1.0.0; extra == "full"
Requires-Dist: rfc3986==2.0.0; extra == "full"
Requires-Dist: rich==14.0.0; extra == "full"
Requires-Dist: rpds-py==0.25.1; extra == "full"
Requires-Dist: rsa==4.9.1; extra == "full"
Requires-Dist: ruff==0.11.11; extra == "full"
Requires-Dist: safetensors==0.5.3; extra == "full"
Requires-Dist: scikit-learn>=1.6.1; extra == "full"
Requires-Dist: scipy==1.15.3; extra == "full"
Requires-Dist: scrapy==2.11.0; extra == "full"
Requires-Dist: seaborn==0.13.2; extra == "full"
Requires-Dist: selenium==4.15.2; extra == "full"
Requires-Dist: sentence-transformers==4.1.0; extra == "full"
Requires-Dist: shellingham==1.5.4; extra == "full"
Requires-Dist: six==1.17.0; extra == "full"
Requires-Dist: sniffio==1.3.1; extra == "full"
Requires-Dist: spacy>=3.8.7; extra == "full"
Requires-Dist: SQLAlchemy==2.0.41; extra == "full"
Requires-Dist: starlette==0.45.3; extra == "full"
Requires-Dist: sympy==1.14.0; extra == "full"
Requires-Dist: tenacity==9.1.2; extra == "full"
Requires-Dist: threadpoolctl==3.6.0; extra == "full"
Requires-Dist: tiktoken==0.9.0; extra == "full"
Requires-Dist: tokenizers==0.21.1; extra == "full"
Requires-Dist: tomli==2.2.1; extra == "full"
Requires-Dist: torch==2.0.1; extra == "full"
Requires-Dist: tqdm==4.67.1; extra == "full"
Requires-Dist: transformers>=4.41.0; extra == "full"
Requires-Dist: twine==6.1.0; extra == "full"
Requires-Dist: typer==0.15.4; extra == "full"
Requires-Dist: typing-inspection==0.4.1; extra == "full"
Requires-Dist: typing_extensions==4.13.2; extra == "full"
Requires-Dist: tzdata==2025.2; extra == "full"
Requires-Dist: urllib3==2.4.0; extra == "full"
Requires-Dist: uvicorn==0.34.2; extra == "full"
Requires-Dist: watchfiles==1.0.5; extra == "full"
Requires-Dist: websocket-client==1.8.0; extra == "full"
Requires-Dist: websockets==15.0.1; extra == "full"
Requires-Dist: wrapt==1.17.2; extra == "full"
Requires-Dist: xxhash==3.5.0; extra == "full"
Requires-Dist: yarl==1.20.0; extra == "full"
Requires-Dist: zipp==3.21.0; extra == "full"
Requires-Dist: weaviate-client; extra == "full"
Requires-Dist: qdrant-client; extra == "full"
Requires-Dist: pymilvus; extra == "full"
Requires-Dist: elasticsearch; extra == "full"
Requires-Dist: opensearch-py; extra == "full"
Requires-Dist: astrapy; extra == "full"
Requires-Dist: clickhouse-connect; extra == "full"
Requires-Dist: azure-cosmos; extra == "full"
Requires-Dist: cassandra-driver; extra == "full"
Requires-Dist: azure-search-documents; extra == "full"
Requires-Dist: deeplake; extra == "full"
Requires-Dist: marqo; extra == "full"
Requires-Dist: meilisearch; extra == "full"
Requires-Dist: pymongo; extra == "full"
Requires-Dist: momento; extra == "full"
Requires-Dist: neo4j; extra == "full"
Requires-Dist: tigrisdb; extra == "full"
Requires-Dist: tiledb; extra == "full"
Requires-Dist: timescale-vector; extra == "full"
Requires-Dist: psycopg2-binary; extra == "full"
Requires-Dist: tcvectordb; extra == "full"
Requires-Dist: usearch; extra == "full"
Requires-Dist: vald-client-python; extra == "full"
Requires-Dist: vectara; extra == "full"
Requires-Dist: typesense; extra == "full"
Requires-Dist: xata; extra == "full"
Requires-Dist: zep-python; extra == "full"
Requires-Dist: unstructured; extra == "full"
Requires-Dist: aiofiles; extra == "full"
Requires-Dist: pytest; extra == "full"
Requires-Dist: pytest-asyncio; extra == "full"
Requires-Dist: python-dotenv; extra == "full"
Requires-Dist: fastapi>=0.68.0; extra == "full"
Requires-Dist: uvicorn>=0.15.0; extra == "full"
Requires-Dist: groq>=0.3.0; extra == "full"
Requires-Dist: huggingface-hub>=0.16.0; extra == "full"
Requires-Dist: httpx>=0.23.0; extra == "full"
Requires-Dist: pytest-cov>=2.12.0; extra == "full"
Provides-Extra: all
Requires-Dist: accelerate==1.7.0; extra == "all"
Requires-Dist: aiohappyeyeballs==2.6.1; extra == "all"
Requires-Dist: aiohttp==3.12.2; extra == "all"
Requires-Dist: aiosignal==1.3.2; extra == "all"
Requires-Dist: annotated-types==0.7.0; extra == "all"
Requires-Dist: anthropic==0.52.1; extra == "all"
Requires-Dist: anyio==4.9.0; extra == "all"
Requires-Dist: asgiref==3.8.1; extra == "all"
Requires-Dist: async-timeout==5.0.1; extra == "all"
Requires-Dist: attrs==25.3.0; extra == "all"
Requires-Dist: backoff==2.2.1; extra == "all"
Requires-Dist: backports.tarfile==1.2.0; extra == "all"
Requires-Dist: bcrypt==4.3.0; extra == "all"
Requires-Dist: beautifulsoup4==4.12.2; extra == "all"
Requires-Dist: bitsandbytes>=0.42.0; extra == "all"
Requires-Dist: black==25.1.0; extra == "all"
Requires-Dist: build==1.2.2.post1; extra == "all"
Requires-Dist: cachetools==5.5.2; extra == "all"
Requires-Dist: certifi==2025.4.26; extra == "all"
Requires-Dist: cffi==1.17.1; extra == "all"
Requires-Dist: charset-normalizer==3.4.2; extra == "all"
Requires-Dist: chromadb==1.0.10; extra == "all"
Requires-Dist: click==8.1.8; extra == "all"
Requires-Dist: colorama==0.4.6; extra == "all"
Requires-Dist: coloredlogs==15.0.1; extra == "all"
Requires-Dist: cryptography==45.0.2; extra == "all"
Requires-Dist: datasets==3.6.0; extra == "all"
Requires-Dist: Deprecated==1.2.18; extra == "all"
Requires-Dist: dill==0.3.8; extra == "all"
Requires-Dist: distro==1.9.0; extra == "all"
Requires-Dist: docutils==0.21.2; extra == "all"
Requires-Dist: durationpy==0.10; extra == "all"
Requires-Dist: EbookLib==0.19; extra == "all"
Requires-Dist: ecdsa==0.19.1; extra == "all"
Requires-Dist: eval_type_backport==0.2.2; extra == "all"
Requires-Dist: exceptiongroup==1.3.0; extra == "all"
Requires-Dist: faiss-cpu==1.11.0; extra == "all"
Requires-Dist: fastapi==0.115.9; extra == "all"
Requires-Dist: filelock==3.18.0; extra == "all"
Requires-Dist: flatbuffers==25.2.10; extra == "all"
Requires-Dist: frozenlist==1.6.0; extra == "all"
Requires-Dist: fsspec==2025.3.0; extra == "all"
Requires-Dist: google-auth==2.40.2; extra == "all"
Requires-Dist: googleapis-common-protos==1.70.0; extra == "all"
Requires-Dist: greenlet==3.2.2; extra == "all"
Requires-Dist: grpcio==1.71.0; extra == "all"
Requires-Dist: h11==0.16.0; extra == "all"
Requires-Dist: hippo-api==1.1.0rc3; extra == "all"
Requires-Dist: httpcore==1.0.9; extra == "all"
Requires-Dist: httptools==0.6.4; extra == "all"
Requires-Dist: httpx==0.28.1; extra == "all"
Requires-Dist: huggingface-hub==0.32.0; extra == "all"
Requires-Dist: humanfriendly==10.0; extra == "all"
Requires-Dist: id==1.5.0; extra == "all"
Requires-Dist: idna==3.10; extra == "all"
Requires-Dist: importlib_metadata==8.6.1; extra == "all"
Requires-Dist: importlib_resources==6.5.2; extra == "all"
Requires-Dist: iniconfig==2.1.0; extra == "all"
Requires-Dist: isort==6.0.1; extra == "all"
Requires-Dist: jaraco.classes==3.4.0; extra == "all"
Requires-Dist: jaraco.context==6.0.1; extra == "all"
Requires-Dist: jaraco.functools==4.1.0; extra == "all"
Requires-Dist: Jinja2==3.1.6; extra == "all"
Requires-Dist: jiter==0.10.0; extra == "all"
Requires-Dist: joblib==1.5.1; extra == "all"
Requires-Dist: jsonschema==4.23.0; extra == "all"
Requires-Dist: jsonschema-specifications==2025.4.1; extra == "all"
Requires-Dist: keyring==25.6.0; extra == "all"
Requires-Dist: kubernetes==32.0.1; extra == "all"
Requires-Dist: lxml==5.4.0; extra == "all"
Requires-Dist: markdown-it-py==3.0.0; extra == "all"
Requires-Dist: MarkupSafe==3.0.2; extra == "all"
Requires-Dist: matplotlib==3.10.3; extra == "all"
Requires-Dist: mdurl==0.1.2; extra == "all"
Requires-Dist: mistralai==1.8.1; extra == "all"
Requires-Dist: mmh3==5.1.0; extra == "all"
Requires-Dist: more-itertools==10.7.0; extra == "all"
Requires-Dist: mpmath==1.3.0; extra == "all"
Requires-Dist: multidict==6.4.4; extra == "all"
Requires-Dist: multiprocess==0.70.16; extra == "all"
Requires-Dist: mypy==1.15.0; extra == "all"
Requires-Dist: mypy_extensions==1.1.0; extra == "all"
Requires-Dist: networkx==3.4.2; extra == "all"
Requires-Dist: nh3==0.2.21; extra == "all"
Requires-Dist: nltk==3.9.1; extra == "all"
Requires-Dist: numpy>=2.2.6; extra == "all"
Requires-Dist: oauthlib==3.2.2; extra == "all"
Requires-Dist: onnxruntime>=1.22.0; extra == "all"
Requires-Dist: onnx>=1.18.0; extra == "all"
Requires-Dist: openai==1.82.0; extra == "all"
Requires-Dist: opencv-python==4.11.0.86; extra == "all"
Requires-Dist: opentelemetry-api==1.33.1; extra == "all"
Requires-Dist: opentelemetry-exporter-otlp-proto-common==1.33.1; extra == "all"
Requires-Dist: opentelemetry-exporter-otlp-proto-grpc==1.33.1; extra == "all"
Requires-Dist: opentelemetry-instrumentation==0.54b1; extra == "all"
Requires-Dist: opentelemetry-instrumentation-asgi==0.54b1; extra == "all"
Requires-Dist: opentelemetry-instrumentation-fastapi==0.54b1; extra == "all"
Requires-Dist: opentelemetry-proto==1.33.1; extra == "all"
Requires-Dist: opentelemetry-sdk==1.33.1; extra == "all"
Requires-Dist: opentelemetry-semantic-conventions==0.54b1; extra == "all"
Requires-Dist: opentelemetry-util-http==0.54b1; extra == "all"
Requires-Dist: orjson==3.10.18; extra == "all"
Requires-Dist: overrides==7.7.0; extra == "all"
Requires-Dist: packaging==25.0; extra == "all"
Requires-Dist: pandas>=2.2.3; extra == "all"
Requires-Dist: pathspec==0.12.1; extra == "all"
Requires-Dist: pdf2image==1.17.0; extra == "all"
Requires-Dist: peft>=0.7.0; extra == "all"
Requires-Dist: pillow==11.2.1; extra == "all"
Requires-Dist: pinecone-client==6.0.0; extra == "all"
Requires-Dist: pinecone-plugin-interface==0.0.7; extra == "all"
Requires-Dist: platformdirs==4.3.8; extra == "all"
Requires-Dist: pluggy==1.6.0; extra == "all"
Requires-Dist: posthog==4.1.0; extra == "all"
Requires-Dist: propcache==0.3.1; extra == "all"
Requires-Dist: protobuf==5.29.4; extra == "all"
Requires-Dist: psutil==7.0.0; extra == "all"
Requires-Dist: pyarrow==20.0.0; extra == "all"
Requires-Dist: pyasn1==0.6.1; extra == "all"
Requires-Dist: pyasn1_modules==0.4.1; extra == "all"
Requires-Dist: pycparser==2.22; extra == "all"
Requires-Dist: pydantic==2.11.5; extra == "all"
Requires-Dist: pydantic_core==2.33.2; extra == "all"
Requires-Dist: pydantic-settings==2.4.0; extra == "all"
Requires-Dist: Pygments==2.19.1; extra == "all"
Requires-Dist: PyPDF2==3.0.1; extra == "all"
Requires-Dist: PyPika==0.48.9; extra == "all"
Requires-Dist: pyproject_hooks==1.2.0; extra == "all"
Requires-Dist: pyreadline3==3.5.4; extra == "all"
Requires-Dist: pytesseract==0.3.13; extra == "all"
Requires-Dist: pytest==8.3.5; extra == "all"
Requires-Dist: pytest-asyncio==1.0.0; extra == "all"
Requires-Dist: python-dateutil==2.9.0.post0; extra == "all"
Requires-Dist: python-docx==1.1.2; extra == "all"
Requires-Dist: python-dotenv==1.1.0; extra == "all"
Requires-Dist: python-jose==3.5.0; extra == "all"
Requires-Dist: python-multipart==0.0.20; extra == "all"
Requires-Dist: pytz==2025.2; extra == "all"
Requires-Dist: pywin32-ctypes==0.2.3; extra == "all"
Requires-Dist: PyYAML==6.0.2; extra == "all"
Requires-Dist: readme_renderer==44.0; extra == "all"
Requires-Dist: referencing==0.36.2; extra == "all"
Requires-Dist: regex==2024.11.6; extra == "all"
Requires-Dist: requests==2.32.3; extra == "all"
Requires-Dist: requests-oauthlib==2.0.0; extra == "all"
Requires-Dist: requests-toolbelt==1.0.0; extra == "all"
Requires-Dist: rfc3986==2.0.0; extra == "all"
Requires-Dist: rich==14.0.0; extra == "all"
Requires-Dist: rpds-py==0.25.1; extra == "all"
Requires-Dist: rsa==4.9.1; extra == "all"
Requires-Dist: ruff==0.11.11; extra == "all"
Requires-Dist: safetensors==0.5.3; extra == "all"
Requires-Dist: scikit-learn>=1.6.1; extra == "all"
Requires-Dist: scipy==1.15.3; extra == "all"
Requires-Dist: scrapy==2.11.0; extra == "all"
Requires-Dist: seaborn==0.13.2; extra == "all"
Requires-Dist: selenium==4.15.2; extra == "all"
Requires-Dist: sentence-transformers==4.1.0; extra == "all"
Requires-Dist: shellingham==1.5.4; extra == "all"
Requires-Dist: six==1.17.0; extra == "all"
Requires-Dist: sniffio==1.3.1; extra == "all"
Requires-Dist: spacy>=3.8.7; extra == "all"
Requires-Dist: SQLAlchemy==2.0.41; extra == "all"
Requires-Dist: starlette==0.45.3; extra == "all"
Requires-Dist: sympy==1.14.0; extra == "all"
Requires-Dist: tenacity==9.1.2; extra == "all"
Requires-Dist: threadpoolctl==3.6.0; extra == "all"
Requires-Dist: tiktoken==0.9.0; extra == "all"
Requires-Dist: tokenizers==0.21.1; extra == "all"
Requires-Dist: tomli==2.2.1; extra == "all"
Requires-Dist: torch==2.0.1; extra == "all"
Requires-Dist: tqdm==4.67.1; extra == "all"
Requires-Dist: transformers>=4.41.0; extra == "all"
Requires-Dist: twine==6.1.0; extra == "all"
Requires-Dist: typer==0.15.4; extra == "all"
Requires-Dist: typing-inspection==0.4.1; extra == "all"
Requires-Dist: typing_extensions==4.13.2; extra == "all"
Requires-Dist: tzdata==2025.2; extra == "all"
Requires-Dist: urllib3==2.4.0; extra == "all"
Requires-Dist: uvicorn==0.34.2; extra == "all"
Requires-Dist: watchfiles==1.0.5; extra == "all"
Requires-Dist: websocket-client==1.8.0; extra == "all"
Requires-Dist: websockets==15.0.1; extra == "all"
Requires-Dist: wrapt==1.17.2; extra == "all"
Requires-Dist: xxhash==3.5.0; extra == "all"
Requires-Dist: yarl==1.20.0; extra == "all"
Requires-Dist: zipp==3.21.0; extra == "all"
Requires-Dist: weaviate-client; extra == "all"
Requires-Dist: qdrant-client; extra == "all"
Requires-Dist: pymilvus; extra == "all"
Requires-Dist: elasticsearch; extra == "all"
Requires-Dist: opensearch-py; extra == "all"
Requires-Dist: astrapy; extra == "all"
Requires-Dist: clickhouse-connect; extra == "all"
Requires-Dist: azure-cosmos; extra == "all"
Requires-Dist: cassandra-driver; extra == "all"
Requires-Dist: azure-search-documents; extra == "all"
Requires-Dist: deeplake; extra == "all"
Requires-Dist: marqo; extra == "all"
Requires-Dist: meilisearch; extra == "all"
Requires-Dist: pymongo; extra == "all"
Requires-Dist: momento; extra == "all"
Requires-Dist: neo4j; extra == "all"
Requires-Dist: tigrisdb; extra == "all"
Requires-Dist: tiledb; extra == "all"
Requires-Dist: timescale-vector; extra == "all"
Requires-Dist: psycopg2-binary; extra == "all"
Requires-Dist: tcvectordb; extra == "all"
Requires-Dist: usearch; extra == "all"
Requires-Dist: vald-client-python; extra == "all"
Requires-Dist: vectara; extra == "all"
Requires-Dist: typesense; extra == "all"
Requires-Dist: xata; extra == "all"
Requires-Dist: zep-python; extra == "all"
Requires-Dist: unstructured; extra == "all"
Requires-Dist: aiofiles; extra == "all"
Requires-Dist: pytest; extra == "all"
Requires-Dist: pytest-asyncio; extra == "all"
Requires-Dist: python-dotenv; extra == "all"
Requires-Dist: fastapi>=0.68.0; extra == "all"
Requires-Dist: uvicorn>=0.15.0; extra == "all"
Requires-Dist: groq>=0.3.0; extra == "all"
Requires-Dist: huggingface-hub>=0.16.0; extra == "all"
Requires-Dist: httpx>=0.23.0; extra == "all"
Requires-Dist: pytest-cov>=2.12.0; extra == "all"
Requires-Dist: cryptography>=41.0.0; extra == "all"
Requires-Dist: pyjwt>=2.8.0; extra == "all"
Requires-Dist: bcrypt>=4.0.0; extra == "all"
Requires-Dist: pytest>=7.0.0; extra == "all"
Requires-Dist: pytest-asyncio>=0.21.0; extra == "all"
Requires-Dist: black>=23.0.0; extra == "all"
Requires-Dist: isort>=5.12.0; extra == "all"
Requires-Dist: mypy>=1.0.0; extra == "all"
Requires-Dist: ruff>=0.1.0; extra == "all"
Requires-Dist: pre-commit>=3.0.0; extra == "all"
Dynamic: author
Dynamic: author-email
Dynamic: classifier
Dynamic: description
Dynamic: description-content-type
Dynamic: home-page
Dynamic: keywords
Dynamic: license-file
Dynamic: project-url
Dynamic: provides-extra
Dynamic: requires-dist
Dynamic: requires-python
Dynamic: summary
